model_metrics_upload/__init__.py
model_metrics_upload/upload.py
model_metrics_upload-1.0.1.dist-info/LICENSE
model_metrics_upload-1.0.1.dist-info/METADATA
model_metrics_upload-1.0.1.dist-info/WHEEL
model_metrics_upload-1.0.1.dist-info/top_level.txt
model_metrics_upload-1.0.1.dist-info/RECORD
