Metadata-Version: 2.1
Name: model-metrics-upload
Version: 1.0.1
Summary: upload model params to target address
Home-page: UNKNOWN
Author: admin
Author-email: 111@google.com
License: UNKNOWN
Platform: UNKNOWN
Classifier: Programming Language :: Python :: 3.9
Classifier: License :: OSI Approved :: MIT License
Classifier: Operating System :: OS Independent
Requires-Python: >=3.6
License-File: LICENSE
Requires-Dist: requests
